README.md
setup.py
afid/__init__.py
afid/afid_qp.py
afid/utils.py
afid.egg-info/PKG-INFO
afid.egg-info/SOURCES.txt
afid.egg-info/dependency_links.txt
afid.egg-info/not-zip-safe
afid.egg-info/requires.txt
afid.egg-info/top_level.txt