Metadata-Version: 1.0
Name: afid
Version: 0.1.2
Summary: Fast affine transformations to incorporate side-information
Home-page: http://github.com/rs239/afid
Author: Rohit Singh
Author-email: rsingh@alum.mit.edu
License: MIT
Platform: UNKNOWN
